matrixbot/__init__.py
matrixbot/cache.py
matrixbot/matrixbot.py
tests/__init__.py
tests/test_cache.py
tests/test_matrixbot.py
python_matrixbot-0.0.7.dist-info/LICENSE
python_matrixbot-0.0.7.dist-info/METADATA
python_matrixbot-0.0.7.dist-info/WHEEL
python_matrixbot-0.0.7.dist-info/top_level.txt
python_matrixbot-0.0.7.dist-info/RECORD
