Metadata-Version: 2.1
Name: python-matrixbot
Version: 0.0.7
Summary: A basic bot for Matrix
Home-page: https://gitlab.com/gibberfish/python-matrixbot
Author: Brian Ó
Author-email: blacksam@gibberfish.org
License: UNKNOWN
Project-URL: Donations, https://gibberfish.org/donate/
Project-URL: Source, https://gitlab.com/gibberfish/python-matrixbot
Project-URL: Issues, https://gitlab.com/gibberfish/python-matrixbot/issues
Keywords: bot botscript chat matrix
Platform: UNKNOWN
Classifier: Programming Language :: Python :: 3
Classifier: License :: OSI Approved :: MIT License
Classifier: Operating System :: OS Independent
Requires-Python: ~=3.6
Requires-Dist: markdown
Requires-Dist: matrix-client
